pytest_raisin.py
pytest_raisin-0.4.dist-info/entry_points.txt
pytest_raisin-0.4.dist-info/WHEEL
pytest_raisin-0.4.dist-info/METADATA
pytest_raisin-0.4.dist-info/RECORD
